tiktokencost/__init__.py
tiktokencost/cost_calculator.py
tiktokencost/exceptions.py
tiktokencost/models.py
tiktokencost/utils.py
TikTokenCost-0.3.dist-info/METADATA
TikTokenCost-0.3.dist-info/WHEEL
TikTokenCost-0.3.dist-info/top_level.txt
TikTokenCost-0.3.dist-info/RECORD
